Metadata-Version: 2.1
Name: django-my-web-console
Version: 0.1.1
Summary: A simple web console based on Django.
Author: yuhua.yang
